api.py
my_httpserver-0.3.0.dist-info/METADATA
my_httpserver-0.3.0.dist-info/WHEEL
my_httpserver-0.3.0.dist-info/entry_points.txt
my_httpserver-0.3.0.dist-info/top_level.txt
my_httpserver-0.3.0.dist-info/RECORD
